cmscribe/__init__.py
cmscribe/main.py
cmscribe/core/__init__.py
cmscribe/core/cache.py
cmscribe/core/config.py
cmscribe/core/types.py
cmscribe/providers/__init__.py
cmscribe/providers/anthropic.py
cmscribe/providers/azure_openai.py
cmscribe/providers/base.py
cmscribe/providers/gemini.py
cmscribe/providers/huggingface.py
cmscribe/providers/ollama.py
cmscribe/providers/openai.py
cmscribe/utils/__init__.py
cmscribe/utils/cmd_.py
cmscribe/utils/git_.py
cmscribe-0.1.0.dist-info/METADATA
cmscribe-0.1.0.dist-info/WHEEL
cmscribe-0.1.0.dist-info/entry_points.txt
cmscribe-0.1.0.dist-info/licenses/LICENSE
cmscribe-0.1.0.dist-info/RECORD
