Metadata-Version: 2.4
Name: cmscribe
Version: 0.1.0
Summary: AI-powered commit message generator
Project-URL: Homepage, https://github.com/quantum-ernest/cmscribe
Project-URL: Issues, https://github.com/quantum-ernest/cmscribe/issues
Author-email: Ernest Asare <ernestasare2411@gmail.com>
License-Expression: GPL-3.0-only
License-File: LICENSE
Requires-Python: >=3.11
Requires-Dist: gitpython>=3.1.41
Requires-Dist: numpy>=1.26.3
Requires-Dist: onnxruntime>=1.17.0
Requires-Dist: requests>=2.31.0
Requires-Dist: tokenizers>=0.15.2
Requires-Dist: transformers>=4.37.2
